{
  "meta": {
    "window_weeks": 10,
    "window_start": "2026-03-16",
    "window_end": "2026-05-18",
    "n_factors_loaded": 50,
    "factors_source": "resultados/test_2_categ_factors.json",
    "n_quiebres": 86702,
    "tuned_test1": {
      "SERVICE_BASE_SHORT_WEEKS": 4,
      "SERVICE_BASE_LONG_WEEKS": 16,
      "SERVICE_RATIO_COLLAPSE": 0.4,
      "SERVICE_RATIO_HOLD": 0.9,
      "SERVICE_DOWN_W_SHORT": 0.5,
      "HEUR_BIAS": 0.8,
      "CROSTON_ALPHA": 0.25,
      "SBA_ALPHA": 0.2,
      "SI_CEIL": 3.0,
      "SI_SKU_ADJ_ALPHA_HIGH": 0.2,
      "SI_MIN_YEARS_FOR_SKU": 2,
      "FAIR_SHARE_TRIED_PENALTY": 0.05
    },
    "excluded_categs_n": 32,
    "n_rows_clean": 63409,
    "n_rows_with_factor": 81759,
    "pct_coverage_factor": 50.99
  },
  "configs": {
    "A": "baseline v3.46 (motor productivo)",
    "B": "Test 1 tuning (12 hyperparams)",
    "C": "v3.47 categ_calib (baseline + factor categ x abc)",
    "D": "combo Test 1 + categ_calib"
  },
  "total": {
    "label": "TOTAL (sin cig/snack, sin quiebres)",
    "A_baseline": {
      "n_rows": 63409,
      "real": 266121.0,
      "fcst": 205100.60271229112,
      "WAPE": 48.65,
      "BIAS": 22.93
    },
    "B_test1": {
      "n_rows": 63409,
      "real": 266121.0,
      "fcst": 201399.15223530307,
      "WAPE": 49.29,
      "BIAS": 24.32
    },
    "C_categ_calib": {
      "n_rows": 63409,
      "real": 266121.0,
      "fcst": 237757.0537731068,
      "WAPE": 48.69,
      "BIAS": 10.66
    },
    "D_combo": {
      "n_rows": 63409,
      "real": 266121.0,
      "fcst": 233673.1198641754,
      "WAPE": 49.2,
      "BIAS": 12.19
    }
  },
  "cervezas": {
    "label": "CERVEZAS",
    "A_baseline": {
      "n_rows": 10523,
      "real": 109126.0,
      "fcst": 88981.77729835952,
      "WAPE": 45.7,
      "BIAS": 18.46
    },
    "B_test1": {
      "n_rows": 10523,
      "real": 109126.0,
      "fcst": 86866.54796421598,
      "WAPE": 45.6,
      "BIAS": 20.4
    },
    "C_categ_calib": {
      "n_rows": 10523,
      "real": 109126.0,
      "fcst": 104745.11211446678,
      "WAPE": 45.06,
      "BIAS": 4.01
    },
    "D_combo": {
      "n_rows": 10523,
      "real": 109126.0,
      "fcst": 102361.02272279537,
      "WAPE": 44.54,
      "BIAS": 6.2
    }
  },
  "sku_9407_stella": {
    "label": "SKU 9407 Stella (testigo lag)",
    "A_baseline": {
      "n_rows": 115,
      "real": 10166.0,
      "fcst": 7296.816369036936,
      "WAPE": 45.96,
      "BIAS": 28.22
    },
    "B_test1": {
      "n_rows": 115,
      "real": 10166.0,
      "fcst": 6511.873390168337,
      "WAPE": 43.92,
      "BIAS": 35.94
    },
    "C_categ_calib": {
      "n_rows": 115,
      "real": 10166.0,
      "fcst": 9485.861279748016,
      "WAPE": 44.87,
      "BIAS": 6.69
    },
    "D_combo": {
      "n_rows": 115,
      "real": 10166.0,
      "fcst": 8465.43540721884,
      "WAPE": 36.61,
      "BIAS": 16.73
    }
  },
  "weekly": [
    {
      "week": "2026-03-16",
      "A_WAPE": 49.33,
      "A_BIAS": -0.03,
      "B_WAPE": 49.11,
      "B_BIAS": 1.24,
      "C_WAPE": 55.56,
      "C_BIAS": -16.62,
      "D_WAPE": 55.06,
      "D_BIAS": -14.96
    },
    {
      "week": "2026-03-23",
      "A_WAPE": 45.93,
      "A_BIAS": 12.77,
      "B_WAPE": 45.72,
      "B_BIAS": 16.66,
      "C_WAPE": 48.12,
      "C_BIAS": -1.89,
      "D_WAPE": 46.82,
      "D_BIAS": 2.76
    },
    {
      "week": "2026-03-30",
      "A_WAPE": 49.34,
      "A_BIAS": 36.08,
      "B_WAPE": 51.27,
      "B_BIAS": 39.87,
      "C_WAPE": 45.93,
      "C_BIAS": 25.28,
      "D_WAPE": 47.49,
      "D_BIAS": 29.76
    },
    {
      "week": "2026-04-06",
      "A_WAPE": 46.78,
      "A_BIAS": 21.54,
      "B_WAPE": 47.54,
      "B_BIAS": 24.04,
      "C_WAPE": 46.76,
      "C_BIAS": 8.1,
      "D_WAPE": 46.58,
      "D_BIAS": 10.98
    },
    {
      "week": "2026-04-13",
      "A_WAPE": 54.04,
      "A_BIAS": 8.15,
      "B_WAPE": 53.71,
      "B_BIAS": 10.08,
      "C_WAPE": 58.54,
      "C_BIAS": -5.77,
      "D_WAPE": 57.65,
      "D_BIAS": -3.68
    },
    {
      "week": "2026-04-20",
      "A_WAPE": 48.64,
      "A_BIAS": 29.33,
      "B_WAPE": 50.04,
      "B_BIAS": 28.25,
      "C_WAPE": 46.56,
      "C_BIAS": 18.74,
      "D_WAPE": 48.51,
      "D_BIAS": 17.34
    },
    {
      "week": "2026-04-27",
      "A_WAPE": 49.17,
      "A_BIAS": 31.72,
      "B_WAPE": 49.77,
      "B_BIAS": 31.02,
      "C_WAPE": 46.77,
      "C_BIAS": 21.59,
      "D_WAPE": 47.96,
      "D_BIAS": 20.53
    },
    {
      "week": "2026-05-04",
      "A_WAPE": 46.85,
      "A_BIAS": 25.04,
      "B_WAPE": 47.84,
      "B_BIAS": 26.67,
      "C_WAPE": 47.0,
      "C_BIAS": 13.43,
      "D_WAPE": 48.29,
      "D_BIAS": 14.97
    },
    {
      "week": "2026-05-11",
      "A_WAPE": 47.38,
      "A_BIAS": 22.94,
      "B_WAPE": 48.38,
      "B_BIAS": 23.25,
      "C_WAPE": 47.17,
      "C_BIAS": 11.33,
      "D_WAPE": 48.26,
      "D_BIAS": 11.45
    },
    {
      "week": "2026-05-18",
      "A_WAPE": 48.79,
      "A_BIAS": 33.6,
      "B_WAPE": 48.8,
      "B_BIAS": 32.5,
      "C_WAPE": 46.47,
      "C_BIAS": 23.45,
      "D_WAPE": 47.1,
      "D_BIAS": 22.03
    }
  ],
  "top_categorias": [
    {
      "categ_id": 1625,
      "name": "Bebidas Alcohólicas / Cervezas / Cervezas ",
      "real": 36842.0,
      "A_WAPE": 50.23,
      "A_BIAS": 10.45,
      "B_WAPE": 50.24,
      "B_BIAS": 12.11,
      "C_WAPE": 51.95,
      "C_BIAS": 3.18,
      "D_WAPE": 51.77,
      "D_BIAS": 4.9
    },
    {
      "categ_id": 1624,
      "name": "Bebidas Alcohólicas / Cervezas / Cervezas ",
      "real": 35162.0,
      "A_WAPE": 41.61,
      "A_BIAS": 26.41,
      "B_WAPE": 41.06,
      "B_BIAS": 30.67,
      "C_WAPE": 38.77,
      "C_BIAS": 4.54,
      "D_WAPE": 35.56,
      "D_BIAS": 10.08
    },
    {
      "categ_id": 1618,
      "name": "Bebidas No Alcohólicas / Bebidas Gaseosas ",
      "real": 23062.0,
      "A_WAPE": 33.17,
      "A_BIAS": 7.9,
      "B_WAPE": 33.9,
      "B_BIAS": 8.71,
      "C_WAPE": 33.91,
      "C_BIAS": 0.49,
      "D_WAPE": 34.66,
      "D_BIAS": 1.38
    },
    {
      "categ_id": 1623,
      "name": "Bebidas Alcohólicas / Cervezas / Cervezas ",
      "real": 22661.0,
      "A_WAPE": 42.67,
      "A_BIAS": 24.9,
      "B_WAPE": 42.33,
      "B_BIAS": 21.76,
      "C_WAPE": 41.23,
      "C_BIAS": 2.37,
      "D_WAPE": 43.26,
      "D_BIAS": -1.71
    },
    {
      "categ_id": 1631,
      "name": "Bebidas Alcohólicas / Cócteles y Licores /",
      "real": 16005.0,
      "A_WAPE": 52.48,
      "A_BIAS": 30.07,
      "B_WAPE": 53.1,
      "B_BIAS": 29.21,
      "C_WAPE": 53.06,
      "C_BIAS": 9.09,
      "D_WAPE": 54.71,
      "D_BIAS": 7.97
    },
    {
      "categ_id": 1619,
      "name": "Bebidas No Alcohólicas / Isotónicas y Ener",
      "real": 14009.0,
      "A_WAPE": 41.19,
      "A_BIAS": 4.74,
      "B_WAPE": 41.81,
      "B_BIAS": 6.74,
      "C_WAPE": 41.19,
      "C_BIAS": 4.74,
      "D_WAPE": 41.81,
      "D_BIAS": 6.74
    },
    {
      "categ_id": 1622,
      "name": "Bebidas Alcohólicas / Cervezas / Cervezas ",
      "real": 13302.0,
      "A_WAPE": 48.18,
      "A_BIAS": 6.96,
      "B_WAPE": 49.04,
      "B_BIAS": 12.12,
      "C_WAPE": 48.21,
      "C_BIAS": 5.95,
      "D_WAPE": 49.07,
      "D_BIAS": 11.11
    },
    {
      "categ_id": 1711,
      "name": "Esenciales Hogar / Aseo y Otros / Limpieza",
      "real": 11535.0,
      "A_WAPE": 91.44,
      "A_BIAS": 84.57,
      "B_WAPE": 91.44,
      "B_BIAS": 84.91,
      "C_WAPE": 91.22,
      "C_BIAS": 85.37,
      "D_WAPE": 91.26,
      "D_BIAS": 85.69
    },
    {
      "categ_id": 1652,
      "name": "Bebidas Alcohólicas / Vinos / Formatos Eco",
      "real": 10456.0,
      "A_WAPE": 49.31,
      "A_BIAS": 14.03,
      "B_WAPE": 51.21,
      "B_BIAS": 16.06,
      "C_WAPE": 51.33,
      "C_BIAS": 1.55,
      "D_WAPE": 53.13,
      "D_BIAS": 3.88
    },
    {
      "categ_id": 1666,
      "name": "Congelados / Hielo",
      "real": 8655.0,
      "A_WAPE": 28.57,
      "A_BIAS": 16.56,
      "B_WAPE": 28.61,
      "B_BIAS": 16.48,
      "C_WAPE": 27.48,
      "C_BIAS": -0.0,
      "D_WAPE": 27.39,
      "D_BIAS": -0.09
    },
    {
      "categ_id": 1617,
      "name": "Bebidas No Alcohólicas / Bebidas Gaseosas ",
      "real": 6713.0,
      "A_WAPE": 42.56,
      "A_BIAS": 21.72,
      "B_WAPE": 43.79,
      "B_BIAS": 21.84,
      "C_WAPE": 43.71,
      "C_BIAS": 3.98,
      "D_WAPE": 45.29,
      "D_BIAS": 4.13
    },
    {
      "categ_id": 1615,
      "name": "Bebidas No Alcohólicas / Bebidas Gaseosas ",
      "real": 6661.0,
      "A_WAPE": 41.89,
      "A_BIAS": 11.99,
      "B_WAPE": 43.29,
      "B_BIAS": 13.71,
      "C_WAPE": 43.71,
      "C_BIAS": 0.35,
      "D_WAPE": 44.65,
      "D_BIAS": 2.31
    },
    {
      "categ_id": 1637,
      "name": "Bebidas Alcohólicas / Destilados / Pisco",
      "real": 4960.0,
      "A_WAPE": 44.6,
      "A_BIAS": 19.83,
      "B_WAPE": 45.62,
      "B_BIAS": 21.28,
      "C_WAPE": 44.66,
      "C_BIAS": 4.81,
      "D_WAPE": 45.48,
      "D_BIAS": 6.45
    },
    {
      "categ_id": 1693,
      "name": "Esenciales Hogar / Panadería / Queques y M",
      "real": 4741.0,
      "A_WAPE": 57.15,
      "A_BIAS": 40.74,
      "B_WAPE": 54.94,
      "B_BIAS": 36.6,
      "C_WAPE": 53.77,
      "C_BIAS": 22.96,
      "D_WAPE": 52.01,
      "D_BIAS": 17.58
    },
    {
      "categ_id": 1608,
      "name": "Bebidas No Alcohólicas / Aguas / Agua Mine",
      "real": 4678.0,
      "A_WAPE": 42.16,
      "A_BIAS": 16.53,
      "B_WAPE": 45.08,
      "B_BIAS": 16.94,
      "C_WAPE": 44.47,
      "C_BIAS": 1.3,
      "D_WAPE": 47.5,
      "D_BIAS": 1.79
    },
    {
      "categ_id": 1668,
      "name": "Esenciales Hogar / Despensa / Despensa",
      "real": 4393.0,
      "A_WAPE": 67.69,
      "A_BIAS": 12.06,
      "B_WAPE": 70.96,
      "B_BIAS": 17.44,
      "C_WAPE": 64.95,
      "C_BIAS": 18.96,
      "D_WAPE": 68.95,
      "D_BIAS": 23.88
    },
    {
      "categ_id": 1650,
      "name": "Bebidas Alcohólicas / Vinos / Formato Está",
      "real": 3798.0,
      "A_WAPE": 68.13,
      "A_BIAS": 50.41,
      "B_WAPE": 69.3,
      "B_BIAS": 51.45,
      "C_WAPE": 68.6,
      "C_BIAS": 35.54,
      "D_WAPE": 69.48,
      "D_BIAS": 36.88
    },
    {
      "categ_id": 1643,
      "name": "Bebidas No Alcohólicas / Jugos / Jugos Col",
      "real": 3701.0,
      "A_WAPE": 46.61,
      "A_BIAS": 18.2,
      "B_WAPE": 48.36,
      "B_BIAS": 19.25,
      "C_WAPE": 48.59,
      "C_BIAS": 0.27,
      "D_WAPE": 50.67,
      "D_BIAS": 1.55
    },
    {
      "categ_id": 1641,
      "name": "Bebidas Alcohólicas / Destilados / Whisky",
      "real": 3698.0,
      "A_WAPE": 52.02,
      "A_BIAS": 18.0,
      "B_WAPE": 54.06,
      "B_BIAS": 20.12,
      "C_WAPE": 53.16,
      "C_BIAS": 6.17,
      "D_WAPE": 54.49,
      "D_BIAS": 8.7
    },
    {
      "categ_id": 1665,
      "name": "Congelados / Helados",
      "real": 3582.0,
      "A_WAPE": 60.91,
      "A_BIAS": 44.24,
      "B_WAPE": 63.03,
      "B_BIAS": 47.0,
      "C_WAPE": 60.37,
      "C_BIAS": 27.51,
      "D_WAPE": 62.15,
      "D_BIAS": 31.1
    },
    {
      "categ_id": 1645,
      "name": "Bebidas No Alcohólicas / Jugos / Jugos Nat",
      "real": 3004.0,
      "A_WAPE": 49.68,
      "A_BIAS": 19.66,
      "B_WAPE": 52.87,
      "B_BIAS": 22.59,
      "C_WAPE": 52.02,
      "C_BIAS": 6.23,
      "D_WAPE": 54.5,
      "D_BIAS": 9.63
    },
    {
      "categ_id": 1612,
      "name": "Bebidas No Alcohólicas / Aguas / Aguas Sab",
      "real": 2985.0,
      "A_WAPE": 49.63,
      "A_BIAS": 24.28,
      "B_WAPE": 52.73,
      "B_BIAS": 26.7,
      "C_WAPE": 51.42,
      "C_BIAS": 5.38,
      "D_WAPE": 54.14,
      "D_BIAS": 8.42
    },
    {
      "categ_id": 1609,
      "name": "Bebidas No Alcohólicas / Aguas / Agua Mine",
      "real": 2820.0,
      "A_WAPE": 44.63,
      "A_BIAS": 22.28,
      "B_WAPE": 47.41,
      "B_BIAS": 24.88,
      "C_WAPE": 46.28,
      "C_BIAS": 0.0,
      "D_WAPE": 48.78,
      "D_BIAS": 3.34
    },
    {
      "categ_id": 1705,
      "name": "Cafetería / Cafetería",
      "real": 2685.0,
      "A_WAPE": 63.88,
      "A_BIAS": 42.69,
      "B_WAPE": 65.05,
      "B_BIAS": 43.81,
      "C_WAPE": 63.88,
      "C_BIAS": 42.69,
      "D_WAPE": 65.05,
      "D_BIAS": 43.81
    },
    {
      "categ_id": 1691,
      "name": "Bebidas No Alcohólicas / Jugos / Jugos y N",
      "real": 2553.0,
      "A_WAPE": 47.96,
      "A_BIAS": 14.24,
      "B_WAPE": 50.37,
      "B_BIAS": 17.13,
      "C_WAPE": 49.35,
      "C_BIAS": 0.88,
      "D_WAPE": 51.88,
      "D_BIAS": 4.1
    },
    {
      "categ_id": 1616,
      "name": "Bebidas No Alcohólicas / Isotónicas y Ener",
      "real": 2542.0,
      "A_WAPE": 43.64,
      "A_BIAS": 14.23,
      "B_WAPE": 46.48,
      "B_BIAS": 19.19,
      "C_WAPE": 45.05,
      "C_BIAS": 3.91,
      "D_WAPE": 47.5,
      "D_BIAS": 9.48
    },
    {
      "categ_id": 1632,
      "name": "Bebidas Alcohólicas / Cócteles y Licores /",
      "real": 1358.0,
      "A_WAPE": 59.16,
      "A_BIAS": 38.56,
      "B_WAPE": 63.21,
      "B_BIAS": 38.79,
      "C_WAPE": 59.54,
      "C_BIAS": 20.12,
      "D_WAPE": 63.91,
      "D_BIAS": 20.43
    },
    {
      "categ_id": 1698,
      "name": "Bebidas Alcohólicas / Vinos / Sangría y Co",
      "real": 1260.0,
      "A_WAPE": 62.01,
      "A_BIAS": 41.13,
      "B_WAPE": 63.76,
      "B_BIAS": 41.2,
      "C_WAPE": 63.76,
      "C_BIAS": 29.28,
      "D_WAPE": 65.49,
      "D_BIAS": 29.56
    },
    {
      "categ_id": 1626,
      "name": "Bebidas Alcohólicas / Cervezas / Cervezas ",
      "real": 1159.0,
      "A_WAPE": 56.2,
      "A_BIAS": 37.9,
      "B_WAPE": 60.28,
      "B_BIAS": 40.59,
      "C_WAPE": 55.41,
      "C_BIAS": 24.51,
      "D_WAPE": 59.95,
      "D_BIAS": 27.69
    },
    {
      "categ_id": 1634,
      "name": "Bebidas Alcohólicas / Cócteles y Licores /",
      "real": 1061.0,
      "A_WAPE": 62.65,
      "A_BIAS": 35.87,
      "B_WAPE": 65.57,
      "B_BIAS": 36.5,
      "C_WAPE": 64.49,
      "C_BIAS": 19.47,
      "D_WAPE": 67.0,
      "D_BIAS": 20.59
    }
  ]
}